biblib/__init__.py
biblib/algo.py
biblib/bib.py
biblib/messages.py
biblib/test.py
biblib_simple-0.1.1.dist-info/LICENSE
biblib_simple-0.1.1.dist-info/METADATA
biblib_simple-0.1.1.dist-info/WHEEL
biblib_simple-0.1.1.dist-info/top_level.txt
biblib_simple-0.1.1.dist-info/RECORD
