Metadata-Version: 1.1
Name: biblib-simple
Version: 0.1.1
Summary: Simple, correct BibTeX parser and algorithms
Home-page: https://github.com/colour-science/biblib
Author: Austin Clements
Author-email: colour-science@googlegroups.com
License: UNKNOWN
Keywords: bibtex,tex
Platform: UNKNOWN
Classifier: Development Status :: 4 - Beta
Classifier: Intended Audience :: Developers
Classifier: Intended Audience :: Science/Research
Classifier: License :: OSI Approved :: MIT License
Classifier: Programming Language :: Python
Classifier: Programming Language :: Python :: 3
Classifier: Topic :: Database
Classifier: Topic :: Text Processing
